bloghunch/__init__.py
bloghunch/main.py
bloghunch-0.1.0.1.dist-info/LICENSE
bloghunch-0.1.0.1.dist-info/METADATA
bloghunch-0.1.0.1.dist-info/WHEEL
bloghunch-0.1.0.1.dist-info/top_level.txt
bloghunch-0.1.0.1.dist-info/RECORD
