Metadata-Version: 2.1
Name: bloghunch
Version: 0.1.0.1
Summary: A Python SDK for the Bloghunch API
Home-page: https://github.com/bloghunch/bh-python-sdk
Author: Bloghunch
Author-email: support@bloghunch.com
Classifier: Development Status :: 3 - Alpha
Classifier: Intended Audience :: Developers
Classifier: License :: OSI Approved :: MIT License
Classifier: Operating System :: OS Independent
Classifier: Programming Language :: Python :: 3
Classifier: Programming Language :: Python :: 3.7
Classifier: Programming Language :: Python :: 3.8
Classifier: Programming Language :: Python :: 3.9
Requires-Python: >=3.7
License-File: LICENSE
Requires-Dist: requests >=2.25.1
